si_fi_o/__init__.py
si_fi_o/app.py
si_fi_o/routes.py
si_fi_o/version.py
si_fi_o/html/home_page.py
si_fi_o/html/session.py
si_fi_o/path/html.py
si_fi_o/path/server.py
si_fi_o/session/constants.py
si_fi_o/session/form.py
si_fi_o/session/session.py
si_fi_o-2025.1.dist-info/METADATA
si_fi_o-2025.1.dist-info/WHEEL
si_fi_o-2025.1.dist-info/top_level.txt
si_fi_o-2025.1.dist-info/RECORD
