Metadata-Version: 2.4
Name: si-fi-o
Version: 2025.1
Summary: SImple Flask IO App Skeleton
Home-page: https://src.koda.cnrs.fr/eric.debreuve/si-fi-o/
Author: Eric Debreuve
Author-email: eric.debreuve@cnrs.fr
License: CeCILL-2.1
Project-URL: Documentation, https://src.koda.cnrs.fr/eric.debreuve/si-fi-o/-/wikis/home
Project-URL: Source, https://src.koda.cnrs.fr/eric.debreuve/si-fi-o/
Keywords: flask,webapp,skeleton,template
Classifier: Topic :: Software Development
Classifier: Intended Audience :: Developers
Classifier: License :: OSI Approved :: CEA CNRS Inria Logiciel Libre License, version 2.1 (CeCILL-2.1)
Classifier: Programming Language :: Python :: 3
Classifier: Development Status :: 4 - Beta
Requires-Python: >=3.10
Requires-Dist: dominate
Requires-Dist: flask
Requires-Dist: flask-bootstrap4
Requires-Dist: flask-session
Requires-Dist: flask-uploads
Requires-Dist: flask-wtf
Requires-Dist: werkzeug
Requires-Dist: wtforms
Dynamic: author
Dynamic: author-email
Dynamic: classifier
Dynamic: description
Dynamic: description-content-type
Dynamic: home-page
Dynamic: keywords
Dynamic: license
Dynamic: project-url
Dynamic: requires-dist
Dynamic: requires-python
Dynamic: summary
